basalam/backbone_api/__init__.py
basalam/backbone_api/exceptions/__init__.py
basalam/backbone_api/exceptions/client_error/__init__.py
basalam/backbone_api/exceptions/client_error/base.py
basalam/backbone_api/exceptions/client_error/conflict.py
basalam/backbone_api/exceptions/client_error/forbidden.py
basalam/backbone_api/exceptions/client_error/handlers.py
basalam/backbone_api/exceptions/client_error/not_found.py
basalam/backbone_api/exceptions/client_error/unauthorized.py
basalam/backbone_api/exceptions/client_error/unprocessable_entity.py
basalam/backbone_api/responses/__init__.py
basalam/backbone_api/responses/response_model_abstract.py
basalam/backbone_api/responses/client_error/__init__.py
basalam/backbone_api/responses/client_error/base.py
basalam/backbone_api/responses/client_error/conflict.py
basalam/backbone_api/responses/client_error/forbidden.py
basalam/backbone_api/responses/client_error/not_found.py
basalam/backbone_api/responses/client_error/unauthorized.py
basalam/backbone_api/responses/client_error/unprocessable_content.py
basalam/backbone_api/responses/models/__init__.py
basalam/backbone_api/responses/models/enum.py
basalam/backbone_api/responses/models/image.py
basalam/backbone_api/responses/models/video.py
basalam/backbone_api/responses/redirection/__init__.py
basalam/backbone_api/responses/server_error/__init__.py
basalam/backbone_api/responses/successful/__init__.py
basalam/backbone_api/responses/successful/bulk.py
basalam/backbone_api/responses/successful/cursor_pagination.py
basalam/backbone_api/responses/successful/multi_status.py
basalam/backbone_api/responses/successful/offset_pagination.py
basalam_backbone_api-0.2.6.dist-info/licenses/LICENSE
basalam_backbone_api-0.2.6.dist-info/METADATA
basalam_backbone_api-0.2.6.dist-info/WHEEL
basalam_backbone_api-0.2.6.dist-info/top_level.txt
basalam_backbone_api-0.2.6.dist-info/RECORD
