Metadata-Version: 2.4
Name: basalam.backbone-api
Version: 0.2.6
Summary: Python OpenApi Utilities for FastAPI
Home-page: https://github.com/basalam/backbone-api
Author: Mohammad Asghari
Author-email: mhmdasghari1@gmail.com
Classifier: Programming Language :: Python :: 3
Classifier: License :: OSI Approved :: MIT License
Classifier: Operating System :: OS Independent
Requires-Python: >=3.6
License-File: LICENSE
Requires-Dist: pydantic>=2.9.1
Requires-Dist: fastapi>=0.114.0
Dynamic: author
Dynamic: author-email
Dynamic: classifier
Dynamic: description
Dynamic: description-content-type
Dynamic: home-page
Dynamic: license-file
Dynamic: requires-dist
Dynamic: requires-python
Dynamic: summary
